geneinfo/__init__.py
geneinfo/intervals.py
geneinfo/utils.py
geneinfo/coords/__init__.py
geneinfo/data/cytoband_hg19.csv
geneinfo/data/cytoband_hg38.csv
geneinfo/data/cytoband_hs1.csv
geneinfo/data/gene_lists.pickle
geneinfo/genelist/__init__.py
geneinfo/information/__init__.py
geneinfo/lift/segment_liftover.py
geneinfo/ontology/__init__.py
geneinfo/plot/__init__.py
geneinfo/plot/chromosome.py
geneinfo/plot/genome.py
geneinfo/plot/region.py
geneinfo/plot/venn.py
geneinfo/string/__init__.py
geneinfo/string/interactions.py
geneinfo-5.6.3.dist-info/licenses/LICENSE
geneinfo-5.6.3.dist-info/METADATA
geneinfo-5.6.3.dist-info/WHEEL
geneinfo-5.6.3.dist-info/top_level.txt
geneinfo-5.6.3.dist-info/RECORD
