Metadata-Version: 2.4
Name: geneinfo
Version: 5.6.3
Summary: ...
Author-email: Kasper Munch <kaspermunch@birc.au.dk>
Project-URL: Homepage, https://munch-group.org/geneinfo
Project-URL: Documentation, https://munch-group.org/geneinfo
Project-URL: Repository, https://github.com/munch-group/geneinfo.git
Project-URL: Issues, https://github.com/munch-group/geneinfo/issues
Classifier: Programming Language :: Python :: 3
Requires-Python: >=3.9
License-File: LICENSE
Requires-Dist: jupyter
Requires-Dist: ipython
Requires-Dist: matplotlib>=3.0
Requires-Dist: seaborn
Requires-Dist: numpy>=1.1
Requires-Dist: requests
Requires-Dist: biopython
Requires-Dist: goatools>=1.2
Requires-Dist: tables
Requires-Dist: wget
Requires-Dist: pydot
Requires-Dist: statsmodels
Requires-Dist: rapidfuzz
Requires-Dist: tqdm
Dynamic: license-file
